hook/__init__.py
hook/hook.py
sceptre_git_clone_hook-1.0.1.dist-info/METADATA
sceptre_git_clone_hook-1.0.1.dist-info/WHEEL
sceptre_git_clone_hook-1.0.1.dist-info/entry_points.txt
sceptre_git_clone_hook-1.0.1.dist-info/top_level.txt
sceptre_git_clone_hook-1.0.1.dist-info/RECORD
