Metadata-Version: 2.1
Name: sceptre-git-clone-hook
Version: 1.0.1
Summary: Git clone hook
Home-page: https://github.com/bilardi/sceptre-git-clone-hook
Author: Alessandra Bilardi
Author-email: alessandra.bilardi@gmail.com
License: Apache2
Keywords: sceptre,sceptre-hook
Platform: UNKNOWN
Classifier: Intended Audience :: Developers
Classifier: Natural Language :: English
Classifier: Environment :: Console
Classifier: Programming Language :: Python :: 2.7
Classifier: Programming Language :: Python :: 3.5
Classifier: Programming Language :: Python :: 3.6
Classifier: Programming Language :: Python :: 3.7
Requires-Dist: packaging (==16.8)
Provides-Extra: test
Requires-Dist: pytest (>=3.2) ; extra == 'test'
